mcp_notebook_data/__init__.py
mcp_notebook_data/_version.py
mcp_notebook_data/py.typed
mcp_notebook_data/server.py
mcp_notebook_data/tools/__init__.py
mcp_notebook_data/tools/notebook.py
mcp_notebook_data/tools/postgresql.py
mcp_notebook_data-0.1.1.dist-info/licenses/LICENSE
mcp_notebook_data-0.1.1.dist-info/METADATA
mcp_notebook_data-0.1.1.dist-info/WHEEL
mcp_notebook_data-0.1.1.dist-info/entry_points.txt
mcp_notebook_data-0.1.1.dist-info/top_level.txt
mcp_notebook_data-0.1.1.dist-info/RECORD
