Metadata-Version: 2.4
Name: mcp-notebook-data
Version: 0.1.1
Summary: Modular notebook data server (MCP) with pluggable tools for Jupyter kernels
Author-email: Roberto Rodriguez <9653181+Cyb3rWard0g@users.noreply.github.com>
License: Apache-2.0
Project-URL: Homepage, https://github.com/Cyb3rWard0g/mcp-notebook-data
Project-URL: Repository, https://github.com/Cyb3rWard0g/mcp-notebook-data
Project-URL: Issues, https://github.com/Cyb3rWard0g/mcp-notebook-data/issues
Keywords: MCP,Jupyter,notebooks,agents,data,server
Classifier: License :: OSI Approved :: Apache Software License
Classifier: Programming Language :: Python :: 3
Classifier: Programming Language :: Python :: 3.11
Classifier: Programming Language :: Python :: 3.12
Classifier: Programming Language :: Python :: 3.13
Requires-Python: >=3.11
License-File: LICENSE
Requires-Dist: fastmcp>=2.11.3
Requires-Dist: mcp>=1.12.4
Requires-Dist: ipykernel>=6.30.1
Requires-Dist: ipywidgets>=8.1.7
Requires-Dist: agent-jupyter-toolkit
Requires-Dist: starlette>=0.47.2
Requires-Dist: uvicorn>=0.35.0
Provides-Extra: dev
Requires-Dist: pytest>=8.4.2; extra == "dev"
Requires-Dist: pytest-asyncio>=0.23; extra == "dev"
Requires-Dist: ruff; extra == "dev"
Requires-Dist: black; extra == "dev"
Requires-Dist: anyio>=4; extra == "dev"
Requires-Dist: build; extra == "dev"
Requires-Dist: twine; extra == "dev"
Requires-Dist: packaging; extra == "dev"
Requires-Dist: setuptools; extra == "dev"
Requires-Dist: setuptools_scm; extra == "dev"
Requires-Dist: wheel; extra == "dev"
Dynamic: license-file
